<annotation>
	<folder>annotations</folder>
	<filename>IMAG0073 (2).JPG</filename>
	<path>D:\OfirL6\Documents\Ben\enclosures_exp\מיון מחדש\annotations\IMAG0073 (2).JPG</path>
	<source>
		<database>Unknown</database>
	</source>
	<size>
		<width>4000</width>
		<height>3000</height>
		<depth>3</depth>
	</size>
	<segmented>0</segmented>
	<object>
		<name>lizard</name>
		<pose>Unspecified</pose>
		<truncated>0</truncated>
		<difficult>0</difficult>
		<bndbox>
			<xmin>1039</xmin>
			<ymin>987</ymin>
			<xmax>1264</xmax>
			<ymax>1100</ymax>
		</bndbox>
	</object>
	<object>
		<name>lizard</name>
		<pose>Unspecified</pose>
		<truncated>0</truncated>
		<difficult>0</difficult>
		<bndbox>
			<xmin>2705</xmin>
			<ymin>878</ymin>
			<xmax>2914</xmax>
			<ymax>959</ymax>
		</bndbox>
	</object>
</annotation>
