<annotation>
	<folder>annotations</folder>
	<filename>IMAG0611.JPG</filename>
	<path>D:\OfirL6\Documents\Ben\enclosures_exp\מיון מחדש\annotations\IMAG0611.JPG</path>
	<source>
		<database>Unknown</database>
	</source>
	<size>
		<width>4000</width>
		<height>3000</height>
		<depth>3</depth>
	</size>
	<segmented>0</segmented>
	<object>
		<name>lizard</name>
		<pose>Unspecified</pose>
		<truncated>0</truncated>
		<difficult>0</difficult>
		<bndbox>
			<xmin>3558</xmin>
			<ymin>866</ymin>
			<xmax>3902</xmax>
			<ymax>1253</ymax>
		</bndbox>
	</object>
	<object>
		<name>lizard</name>
		<pose>Unspecified</pose>
		<truncated>0</truncated>
		<difficult>0</difficult>
		<bndbox>
			<xmin>3077</xmin>
			<ymin>416</ymin>
			<xmax>3267</xmax>
			<ymax>566</ymax>
		</bndbox>
	</object>
	<object>
		<name>lizard</name>
		<pose>Unspecified</pose>
		<truncated>0</truncated>
		<difficult>0</difficult>
		<bndbox>
			<xmin>1627</xmin>
			<ymin>162</ymin>
			<xmax>1923</xmax>
			<ymax>406</ymax>
		</bndbox>
	</object>
</annotation>
